hsi_dataset_api/DataCropper.py
hsi_dataset_api/Dataset.py
hsi_dataset_api/__init__.py
hsi_dataset_api/utils/WrongDirectoryStructure.py
hsi_dataset_api/utils/__init__.py
HSI_Dataset_API-1.5.3.dist-info/LICENSE
HSI_Dataset_API-1.5.3.dist-info/METADATA
HSI_Dataset_API-1.5.3.dist-info/WHEEL
HSI_Dataset_API-1.5.3.dist-info/top_level.txt
HSI_Dataset_API-1.5.3.dist-info/RECORD
