Metadata-Version: 2.1
Name: HSI-Dataset-API
Version: 1.5.3
Summary: API for accessing HSI datasets
Home-page: https://github.com/Banayaki/hsi_dataset_api
Author: Mukhin Artem
Author-email: artemmukhinssau@gmail.com
License: UNKNOWN
Platform: UNKNOWN
Classifier: Programming Language :: Python :: 3
Classifier: Topic :: Software Development :: Libraries :: Python Modules
License-File: LICENSE
